sti/__init__.py
sti/__main__.py
sti/imports/__init__.py
sti/imports/resolve.py
sti/meta/__init__.py
sti/meta/program.py
sti/parse/__init__.py
sti/parse/program.py
stream/__init__.py
stream/__main__.py
stream/_version.py
stream/builtins/__init__.py
stream/builtins/functions/__init__.py
stream/builtins/functions/seasons.py
stream/builtins/keywords/__init__.py
stream/builtins/keywords/comment.py
stream/builtins/keywords/gyge.py
stream/builtins/operators/__init__.py
stream/builtins/operators/assign.py
stream/modules/__init__.py
stream/modules/os/__init__.py
stream/modules/os/fd.py
stream/modules/self/__init__.py
stream/program/__init__.py
stream/program/poc.py
stream_lang-0.1.0.dist-info/METADATA
stream_lang-0.1.0.dist-info/WHEEL
stream_lang-0.1.0.dist-info/entry_points.txt
stream_lang-0.1.0.dist-info/RECORD
