Metadata-Version: 2.4
Name: stream-lang
Version: 0.1.0
Requires-Python: >=3.12
Requires-Dist: pydantic>=2.12.5
Requires-Dist: rich>=14.2.0
Requires-Dist: typer>=0.21.0
Provides-Extra: dev
Requires-Dist: mypy>=1.8.0; extra == 'dev'
Requires-Dist: ruff>=0.9.0; extra == 'dev'
Provides-Extra: docs
Requires-Dist: cairosvg>=2.8.2; extra == 'docs'
Requires-Dist: ghp-import>=2.1.0; extra == 'docs'
Requires-Dist: mkdocs-git-revision-date-localized-plugin>=1.5.0; extra == 'docs'
Requires-Dist: mkdocs-material>=9.7.1; extra == 'docs'
Requires-Dist: mkdocs-rss-plugin>=1.17.7; extra == 'docs'
Requires-Dist: pillow>=12.1.0; extra == 'docs'
Provides-Extra: test
Requires-Dist: pytest>=8.0; extra == 'test'
